stocklens_sdk/__init__.py
stocklens_sdk/indicators.py
stocklens_sdk/news_fetcher.py
stocklens_sdk/predictor.py
stocklens_sdk/sentiment_utils.py
stocklens_sdk/summarizer.py
stocklens_sdk/tts_generator.py
stocklens_sdk-1.0.1.dist-info/METADATA
stocklens_sdk-1.0.1.dist-info/WHEEL
stocklens_sdk-1.0.1.dist-info/top_level.txt
stocklens_sdk-1.0.1.dist-info/RECORD
