Metadata-Version: 2.4
Name: stocklens-sdk
Version: 1.0.1
Summary: AI-Powered Stock Sentiment and Trend Analysis SDK
Home-page: https://github.com/karthikrajesh10/stocklens_sdk
Author: Karthik R S
Author-email: karthikrajesh9010@gmail.com
Classifier: Programming Language :: Python :: 3
Classifier: License :: OSI Approved :: MIT License
Classifier: Operating System :: OS Independent
Requires-Python: >=3.8
Requires-Dist: textblob
Requires-Dist: requests
Requires-Dist: flask
Requires-Dist: flask-cors
Requires-Dist: gtts
Requires-Dist: pandas
Requires-Dist: yfinance
Requires-Dist: scikit-learn
Dynamic: author
Dynamic: author-email
Dynamic: classifier
Dynamic: description
Dynamic: description-content-type
Dynamic: home-page
Dynamic: requires-dist
Dynamic: requires-python
Dynamic: summary
